MANIFEST.in
README.md
requirements.txt
setup.py
sfko/__init__.py
sfko/check.py
sfko/constant.py
sfko/entry.py
sfko/error.py
sfko/execute.py
sfko/load.py
sfko/register.py
sfko/report.py
sfko/s3.py
sfko/stages.py
sfko/test.py
sfko.egg-info/PKG-INFO
sfko.egg-info/SOURCES.txt
sfko.egg-info/dependency_links.txt
sfko.egg-info/entry_points.txt
sfko.egg-info/requires.txt
sfko.egg-info/top_level.txt
sfko/obj/__init__.py
sfko/obj/backend.py
sfko/obj/environment.py
sfko/obj/object.py
sfko/obj/scenario.py
sfko/obj/secret.py
sfko/obj/stage.py
sfko/util/__init__.py
sfko/util/conf.py
sfko/util/iter.py
sfko/util/log.py
sfko/util/mapping.py
sfko/util/parse.py
sfko/util/prng.py
sfko/util/proxy.py
sfko/util/redis.py
sfko/util/schema.py
sfko/util/yaml.py