Metadata-Version: 1.1
Name: sfko
Version: 0.1.4
Summary: A utility for long running semi-random stress tests of Zenko
Home-page: UNKNOWN
Author: Taylor McKinnon
Author-email: taylor.mckinnon@scality.com
License: UNKNOWN
Keywords: scality zenko orbit
Platform: UNKNOWN
Classifier: Development Status :: 3 - Alpha
Classifier: Intended Audience :: Developers
Classifier: License :: OSI Approved :: Apache Software License
Classifier: Programming Language :: Python :: 3
Classifier: Programming Language :: Python :: 3.7
